mythic/__init__.py
mythic/graphql_queries.py
mythic/mythic.py
mythic/mythic_classes.py
mythic/mythic_crypto.py
mythic/mythic_exceptions.py
mythic/mythic_utilities.py
mythic-0.2.10.dist-info/LICENSE
mythic-0.2.10.dist-info/METADATA
mythic-0.2.10.dist-info/WHEEL
mythic-0.2.10.dist-info/top_level.txt
mythic-0.2.10.dist-info/RECORD
