Metadata-Version: 2.1
Name: mythic
Version: 0.2.10
Summary: Interact with Mythic C2 Framework Instances
Home-page: https://docs.mythic-c2.net/scripting
Author: @its_a_feature_
Author-email: 
License: BSD3
Classifier: License :: Other/Proprietary License
Classifier: Programming Language :: Python :: 3.10
License-File: LICENSE
Requires-Dist: aiohttp
Requires-Dist: asyncio
Requires-Dist: gql[aiohttp,websockets] (==3.5.3)
Requires-Dist: pycryptodome
